README.md
setup.cfg
setup.py
aakashdist/Binomialdistribution.py
aakashdist/Gaussiandistribution.py
aakashdist/Generaldistribution.py
aakashdist/__init__.py
aakashdist.egg-info/PKG-INFO
aakashdist.egg-info/SOURCES.txt
aakashdist.egg-info/dependency_links.txt
aakashdist.egg-info/not-zip-safe
aakashdist.egg-info/top_level.txt